[{"uri":"https:\/\/resolver.kb.nl\/resolve?urn=ddd:010962298:mpeg21:p025","img":"1987\/ddd-010962298-mpeg21-p025.jpg","krant":"Het vr\u0133e volk : democratisch-socialistisch dagblad","pagina":"25","datum":"7\/1\/1987"},{"uri":"https:\/\/resolver.kb.nl\/resolve?urn=ddd:010962304:mpeg21:p025","img":"1987\/ddd-010962304-mpeg21-p025.jpg","krant":"Het vr\u0133e volk : democratisch-socialistisch dagblad","pagina":"25","datum":"14\/1\/1987"},{"uri":"https:\/\/resolver.kb.nl\/resolve?urn=KBNRC01:000030416:mpeg21:p027","img":"1987\/KBNRC01-000030416-mpeg21-p027.jpg","krant":"NRC Handelsblad","pagina":"27","datum":"21\/1\/1987"},{"uri":"https:\/\/resolver.kb.nl\/resolve?urn=ddd:010962317:mpeg21:p025","img":"1987\/ddd-010962317-mpeg21-p025.jpg","krant":"Het vr\u0133e volk : democratisch-socialistisch dagblad","pagina":"25","datum":"28\/1\/1987"},{"uri":"https:\/\/resolver.kb.nl\/resolve?urn=ddd:010962323:mpeg21:p035","img":"1987\/ddd-010962323-mpeg21-p035.jpg","krant":"Het vr\u0133e volk : democratisch-socialistisch dagblad","pagina":"35","datum":"4\/2\/1987"},{"uri":"https:\/\/resolver.kb.nl\/resolve?urn=KBNRC01:000034869:mpeg21:p029","img":"1987\/KBNRC01-000034869-mpeg21-p029.jpg","krant":"NRC Handelsblad","pagina":"29","datum":"11\/2\/1987"},{"uri":"https:\/\/resolver.kb.nl\/resolve?urn=ddd:010962335:mpeg21:p027","img":"1987\/ddd-010962335-mpeg21-p027.jpg","krant":"Het vr\u0133e volk : democratisch-socialistisch dagblad","pagina":"27","datum":"18\/2\/1987"},{"uri":"https:\/\/resolver.kb.nl\/resolve?urn=ddd:010962341:mpeg21:p027","img":"1987\/ddd-010962341-mpeg21-p027.jpg","krant":"Het vr\u0133e volk : democratisch-socialistisch dagblad","pagina":"27","datum":"25\/2\/1987"},{"uri":"https:\/\/resolver.kb.nl\/resolve?urn=ddd:010962347:mpeg21:p027","img":"1987\/ddd-010962347-mpeg21-p027.jpg","krant":"Het vr\u0133e volk : democratisch-socialistisch dagblad","pagina":"27","datum":"4\/3\/1987"},{"uri":"https:\/\/resolver.kb.nl\/resolve?urn=ddd:010962353:mpeg21:p027","img":"1987\/ddd-010962353-mpeg21-p027.jpg","krant":"Het vr\u0133e volk : democratisch-socialistisch dagblad","pagina":"27","datum":"11\/3\/1987"},{"uri":"https:\/\/resolver.kb.nl\/resolve?urn=ddd:010962359:mpeg21:p027","img":"1987\/ddd-010962359-mpeg21-p027.jpg","krant":"Het vr\u0133e volk : democratisch-socialistisch dagblad","pagina":"27","datum":"18\/3\/1987"},{"uri":"https:\/\/resolver.kb.nl\/resolve?urn=ddd:010962365:mpeg21:p040","img":"1987\/ddd-010962365-mpeg21-p040.jpg","krant":"Het vr\u0133e volk : democratisch-socialistisch dagblad","pagina":"40","datum":"25\/3\/1987"},{"uri":"https:\/\/resolver.kb.nl\/resolve?urn=ddd:010962371:mpeg21:p029","img":"1987\/ddd-010962371-mpeg21-p029.jpg","krant":"Het vr\u0133e volk : democratisch-socialistisch dagblad","pagina":"29","datum":"1\/4\/1987"},{"uri":"https:\/\/resolver.kb.nl\/resolve?urn=ddd:010962377:mpeg21:p031","img":"1987\/ddd-010962377-mpeg21-p031.jpg","krant":"Het vr\u0133e volk : democratisch-socialistisch dagblad","pagina":"31","datum":"8\/4\/1987"},{"uri":"https:\/\/resolver.kb.nl\/resolve?urn=ddd:010962383:mpeg21:p031","img":"1987\/ddd-010962383-mpeg21-p031.jpg","krant":"Het vr\u0133e volk : democratisch-socialistisch dagblad","pagina":"31","datum":"15\/4\/1987"},{"uri":"https:\/\/resolver.kb.nl\/resolve?urn=ddd:010962389:mpeg21:p027","img":"1987\/ddd-010962389-mpeg21-p027.jpg","krant":"Het vr\u0133e volk : democratisch-socialistisch dagblad","pagina":"27","datum":"22\/4\/1987"},{"uri":"https:\/\/resolver.kb.nl\/resolve?urn=ddd:010962395:mpeg21:p029","img":"1987\/ddd-010962395-mpeg21-p029.jpg","krant":"Het vr\u0133e volk : democratisch-socialistisch dagblad","pagina":"29","datum":"29\/4\/1987"},{"uri":"https:\/\/resolver.kb.nl\/resolve?urn=KBNRC01:000028726:mpeg21:p022","img":"1987\/KBNRC01-000028726-mpeg21-p022.jpg","krant":"NRC Handelsblad","pagina":"22","datum":"6\/5\/1987"},{"uri":"https:\/\/resolver.kb.nl\/resolve?urn=ddd:010962407:mpeg21:p031","img":"1987\/ddd-010962407-mpeg21-p031.jpg","krant":"Het vr\u0133e volk : democratisch-socialistisch dagblad","pagina":"31","datum":"13\/5\/1987"},{"uri":"https:\/\/resolver.kb.nl\/resolve?urn=ddd:010962413:mpeg21:p029","img":"1987\/ddd-010962413-mpeg21-p029.jpg","krant":"Het vr\u0133e volk : democratisch-socialistisch dagblad","pagina":"29","datum":"20\/5\/1987"},{"uri":"https:\/\/resolver.kb.nl\/resolve?urn=ddd:010962419:mpeg21:p033","img":"1987\/ddd-010962419-mpeg21-p033.jpg","krant":"Het vr\u0133e volk : democratisch-socialistisch dagblad","pagina":"33","datum":"27\/5\/1987"},{"uri":"https:\/\/resolver.kb.nl\/resolve?urn=ddd:010962424:mpeg21:p026","img":"1987\/ddd-010962424-mpeg21-p026.jpg","krant":"Het vr\u0133e volk : democratisch-socialistisch dagblad","pagina":"26","datum":"3\/6\/1987"},{"uri":"https:\/\/resolver.kb.nl\/resolve?urn=ddd:010962429:mpeg21:p025","img":"1987\/ddd-010962429-mpeg21-p025.jpg","krant":"Het vr\u0133e volk : democratisch-socialistisch dagblad","pagina":"25","datum":"10\/6\/1987"},{"uri":"https:\/\/resolver.kb.nl\/resolve?urn=ddd:010962435:mpeg21:p024","img":"1987\/ddd-010962435-mpeg21-p024.jpg","krant":"Het vr\u0133e volk : democratisch-socialistisch dagblad","pagina":"24","datum":"17\/6\/1987"},{"uri":"https:\/\/resolver.kb.nl\/resolve?urn=ddd:010962441:mpeg21:p027","img":"1987\/ddd-010962441-mpeg21-p027.jpg","krant":"Het vr\u0133e volk : democratisch-socialistisch dagblad","pagina":"27","datum":"24\/6\/1987"},{"uri":"https:\/\/resolver.kb.nl\/resolve?urn=ddd:010962447:mpeg21:p021","img":"1987\/ddd-010962447-mpeg21-p021.jpg","krant":"Het vr\u0133e volk : democratisch-socialistisch dagblad","pagina":"21","datum":"1\/7\/1987"},{"uri":"https:\/\/resolver.kb.nl\/resolve?urn=ddd:010962453:mpeg21:p023","img":"1987\/ddd-010962453-mpeg21-p023.jpg","krant":"Het vr\u0133e volk : democratisch-socialistisch dagblad","pagina":"23","datum":"8\/7\/1987"},{"uri":"https:\/\/resolver.kb.nl\/resolve?urn=ddd:010962459:mpeg21:p021","img":"1987\/ddd-010962459-mpeg21-p021.jpg","krant":"Het vr\u0133e volk : democratisch-socialistisch dagblad","pagina":"21","datum":"15\/7\/1987"},{"uri":"https:\/\/resolver.kb.nl\/resolve?urn=ddd:010962466:mpeg21:p021","img":"1987\/ddd-010962466-mpeg21-p021.jpg","krant":"Het vr\u0133e volk : democratisch-socialistisch dagblad","pagina":"21","datum":"22\/7\/1987"},{"uri":"https:\/\/resolver.kb.nl\/resolve?urn=ddd:010962472:mpeg21:p019","img":"1987\/ddd-010962472-mpeg21-p019.jpg","krant":"Het vr\u0133e volk : democratisch-socialistisch dagblad","pagina":"19","datum":"29\/7\/1987"},{"uri":"https:\/\/resolver.kb.nl\/resolve?urn=ddd:010962483:mpeg21:p019","img":"1987\/ddd-010962483-mpeg21-p019.jpg","krant":"Het vr\u0133e volk : democratisch-socialistisch dagblad","pagina":"19","datum":"5\/8\/1987"},{"uri":"https:\/\/resolver.kb.nl\/resolve?urn=ddd:010962504:mpeg21:p018","img":"1987\/ddd-010962504-mpeg21-p018.jpg","krant":"Het vr\u0133e volk : democratisch-socialistisch dagblad","pagina":"18","datum":"12\/8\/1987"},{"uri":"https:\/\/resolver.kb.nl\/resolve?urn=ddd:010962510:mpeg21:p021","img":"1987\/ddd-010962510-mpeg21-p021.jpg","krant":"Het vr\u0133e volk : democratisch-socialistisch dagblad","pagina":"21","datum":"19\/8\/1987"},{"uri":"https:\/\/resolver.kb.nl\/resolve?urn=ddd:010962516:mpeg21:p025","img":"1987\/ddd-010962516-mpeg21-p025.jpg","krant":"Het vr\u0133e volk : democratisch-socialistisch dagblad","pagina":"25","datum":"26\/8\/1987"},{"uri":"https:\/\/resolver.kb.nl\/resolve?urn=KBNRC01:000028993:mpeg21:p022","img":"1987\/KBNRC01-000028993-mpeg21-p022.jpg","krant":"NRC Handelsblad","pagina":"22","datum":"2\/9\/1987"},{"uri":"https:\/\/resolver.kb.nl\/resolve?urn=ddd:010962475:mpeg21:p023","img":"1987\/ddd-010962475-mpeg21-p023.jpg","krant":"Het vr\u0133e volk : democratisch-socialistisch dagblad","pagina":"23","datum":"9\/9\/1987"},{"uri":"https:\/\/resolver.kb.nl\/resolve?urn=ddd:010962487:mpeg21:p027","img":"1987\/ddd-010962487-mpeg21-p027.jpg","krant":"Het vr\u0133e volk : democratisch-socialistisch dagblad","pagina":"27","datum":"16\/9\/1987"},{"uri":"https:\/\/resolver.kb.nl\/resolve?urn=ddd:010962497:mpeg21:p022","img":"1987\/ddd-010962497-mpeg21-p022.jpg","krant":"Het vr\u0133e volk : democratisch-socialistisch dagblad","pagina":"22","datum":"23\/9\/1987"},{"uri":"https:\/\/resolver.kb.nl\/resolve?urn=ddd:010962518:mpeg21:p042","img":"1987\/ddd-010962518-mpeg21-p042.jpg","krant":"Het vr\u0133e volk : democratisch-socialistisch dagblad","pagina":"42","datum":"30\/9\/1987"},{"uri":"https:\/\/resolver.kb.nl\/resolve?urn=KBNRC01:000034896:mpeg21:p016","img":"1987\/KBNRC01-000034896-mpeg21-p016.jpg","krant":"NRC Handelsblad","pagina":"16","datum":"7\/10\/1987"},{"uri":"https:\/\/resolver.kb.nl\/resolve?urn=KBNRC01:000034902:mpeg21:p026","img":"1987\/KBNRC01-000034902-mpeg21-p026.jpg","krant":"NRC Handelsblad","pagina":"26","datum":"14\/10\/1987"},{"uri":"https:\/\/resolver.kb.nl\/resolve?urn=KBNRC01:000034908:mpeg21:p028","img":"1987\/KBNRC01-000034908-mpeg21-p028.jpg","krant":"NRC Handelsblad","pagina":"28","datum":"21\/10\/1987"},{"uri":"https:\/\/resolver.kb.nl\/resolve?urn=ddd:010962594:mpeg21:p029","img":"1987\/ddd-010962594-mpeg21-p029.jpg","krant":"Het vr\u0133e volk : democratisch-socialistisch dagblad","pagina":"29","datum":"28\/10\/1987"},{"uri":"https:\/\/resolver.kb.nl\/resolve?urn=ddd:010962600:mpeg21:p027","img":"1987\/ddd-010962600-mpeg21-p027.jpg","krant":"Het vr\u0133e volk : democratisch-socialistisch dagblad","pagina":"27","datum":"4\/11\/1987"},{"uri":"https:\/\/resolver.kb.nl\/resolve?urn=ddd:010962529:mpeg21:p027","img":"1987\/ddd-010962529-mpeg21-p027.jpg","krant":"Het vr\u0133e volk : democratisch-socialistisch dagblad","pagina":"27","datum":"11\/11\/1987"},{"uri":"https:\/\/resolver.kb.nl\/resolve?urn=ddd:010962539:mpeg21:p029","img":"1987\/ddd-010962539-mpeg21-p029.jpg","krant":"Het vr\u0133e volk : democratisch-socialistisch dagblad","pagina":"29","datum":"18\/11\/1987"},{"uri":"https:\/\/resolver.kb.nl\/resolve?urn=ddd:010962545:mpeg21:p026","img":"1987\/ddd-010962545-mpeg21-p026.jpg","krant":"Het vr\u0133e volk : democratisch-socialistisch dagblad","pagina":"26","datum":"25\/11\/1987"},{"uri":"https:\/\/resolver.kb.nl\/resolve?urn=KBNRC01:000029030:mpeg21:p014","img":"1987\/KBNRC01-000029030-mpeg21-p014.jpg","krant":"NRC Handelsblad","pagina":"14","datum":"2\/12\/1987"},{"uri":"https:\/\/resolver.kb.nl\/resolve?urn=ddd:010962564:mpeg21:p026","img":"1987\/ddd-010962564-mpeg21-p026.jpg","krant":"Het vr\u0133e volk : democratisch-socialistisch dagblad","pagina":"26","datum":"9\/12\/1987"},{"uri":"https:\/\/resolver.kb.nl\/resolve?urn=ddd:010962574:mpeg21:p028","img":"1987\/ddd-010962574-mpeg21-p028.jpg","krant":"Het vr\u0133e volk : democratisch-socialistisch dagblad","pagina":"28","datum":"16\/12\/1987"},{"uri":"https:\/\/resolver.kb.nl\/resolve?urn=ddd:010962583:mpeg21:p022","img":"1987\/ddd-010962583-mpeg21-p022.jpg","krant":"Het vr\u0133e volk : democratisch-socialistisch dagblad","pagina":"22","datum":"23\/12\/1987"},{"uri":"https:\/\/resolver.kb.nl\/resolve?urn=ddd:010962590:mpeg21:p012","img":"1987\/ddd-010962590-mpeg21-p012.jpg","krant":"Het vr\u0133e volk : democratisch-socialistisch dagblad","pagina":"12","datum":"30\/12\/1987"}]